README.rst
setup.py
systemd_stopper/__init__.py
systemd_stopper/example_app.py
systemd_stopper/waiter.py
systemd_stopper/wrap.py
systemd_stopper.egg-info/PKG-INFO
systemd_stopper.egg-info/SOURCES.txt
systemd_stopper.egg-info/dependency_links.txt
systemd_stopper.egg-info/top_level.txt