Metadata-Version: 1.1
Name: systemd-stopper
Version: 0.1.0
Summary: A signal handler utility for Python applications running as systemd units
Home-page: https://github.com/chschmitt/systemd-stopper
Author: Christoph Schmitt
Author-email: dev@chschmitt.de
License: BSD License
Keywords: systemd linux signal-handling
Platform: UNKNOWN
Classifier: Development Status :: 3 - Alpha
Classifier: Programming Language :: Python :: 3
Classifier: Programming Language :: Python :: Implementation :: CPython
Classifier: Operating System :: POSIX :: Linux
